COPYING
ChangeLog
INSTALL
MANIFEST.in
README
setup.py
dorrie/__init__.py
dorrie/__init__.pyc
dorrie/manage.py
dorrie/ritpost.txt
dorrie/settings.py
dorrie/settings.pyc
dorrie/settings.py~
dorrie/urls.py
dorrie/urls.pyc
dorrie/comps/__init__.py
dorrie/comps/__init__.pyc
dorrie/comps/comps.py
dorrie/comps/comps.pyc
dorrie/comps/comps.py~
dorrie/comps/forms.py
dorrie/comps/forms.pyc
dorrie/comps/forms.py~
dorrie/comps/hardwareLists.py
dorrie/comps/hardwareLists.pyc
dorrie/comps/helper.py
dorrie/comps/helper.pyc
dorrie/comps/helper.py~
dorrie/comps/models.py
dorrie/comps/models.pyc
dorrie/comps/models.py~
dorrie/comps/parse.py
dorrie/comps/parse.pyc
dorrie/comps/parse.py~
dorrie/comps/views.py
dorrie/comps/views.pyc
dorrie/comps/views.py~
dorrie/comps/media/RIT_Remix.ks
dorrie/comps/media/arrow.png
dorrie/comps/media/border-left.png
dorrie/comps/media/border-right.png
dorrie/comps/media/cc_logo_76x18.png
dorrie/comps/media/dorrie.fedora.css
dorrie/comps/media/dorrie.jpg
dorrie/comps/media/en_google_144x23.png
dorrie/comps/media/faint_box_550x115.png
dorrie/comps/media/faint_box_650x175.png
dorrie/comps/media/fedora-logo.png
dorrie/comps/media/fedora.css
dorrie/comps/media/fedora_gradient_25.png
dorrie/comps/media/fedora_logo_150x46.png
dorrie/comps/media/line-bottom.png
dorrie/comps/media/line.png
dorrie/comps/media/redhat_gradient_25.png
dorrie/comps/media/redhat_logo_150x48.png
dorrie/comps/media/images/about-icon.png
dorrie/comps/media/images/background.png
dorrie/comps/media/images/checkmark.png
dorrie/comps/media/images/community-adammiller.png
dorrie/comps/media/images/community-blank.png
dorrie/comps/media/images/djs.png
dorrie/comps/media/images/down-arrow.png
dorrie/comps/media/images/download-now.png
dorrie/comps/media/images/fedarrow.png
dorrie/comps/media/images/fedarrowbig.png
dorrie/comps/media/images/fedarrowside.png
dorrie/comps/media/images/fedarrowsidebig.png
dorrie/comps/media/images/fedora-dorrie-logo.png
dorrie/comps/media/images/login-icon.png
ritremixerator.egg-info/PKG-INFO
ritremixerator.egg-info/SOURCES.txt
ritremixerator.egg-info/dependency_links.txt
ritremixerator.egg-info/requires.txt
ritremixerator.egg-info/top_level.txt