Metadata-Version: 1.0
Name: ritremixerator
Version: 0.3
Summary: A fork of the Dorrie project to create Spins and Remixes of Fedora.
Home-page: https://github.com/ear7631/RITRemixerator
Author: Eitan Romanoff
Author-email: ear7631@rit.edu
License: AGPL3
Keywords: fedora kickstart python dorrie django redhat rit
Platform: UNKNOWN
Classifier: Development Status :: 3 - Alpha
Classifier: Topic :: Utilities
Classifier: License :: OSI Approved :: GNU Affero General Public License v3
